[
  {
    "id": "1127018667"
  },
  {
    "id": "1835590672"
  },
  {
    "id": "162726413"
  },
  {
    "id": "6670816620"
  },
  {
    "id": "7373120816"
  },
  {
    "id": "7325250501"
  },
  {
    "id": "7624990608"
  },
  {
    "id": "7229931861"
  },
  {
    "id": "7737184144"
  },
  {
    "id": "6249637206"
  },
  {
    "id": "7466582402"
  },
  {
    "id": "6953096364"
  },
  {
    "id": "7183583651"
  },
  {
    "id": "6011359218"
  },
  {
    "id": "8068462990"
  },
  {
    "id": "6305277200"
  },
  {
    "id": "7768163129"
  },
  {
    "id": "8382089859"
  },
  {
    "id": "7083119014"
  },
  {
    "id": "8409923974"
  },
  {
    "id": "8411156571"
  },
  {
    "id": "1040289036"
  },
  {
    "id": "984854914"
  },
  {
    "id": "6948782334"
  },
  {
    "id": "852719312"
  },
  {
    "id": "5839619528"
  },
  {
    "id": "7002688745"
  },
  {
    "id": "7605349939"
  },
  {
    "id": "1330489155"
  },
  {
    "id": "6945466529"
  },
  {
    "id": "7743515384"
  },
  {
    "id": "6807847280"
  },
  {
    "id": "6344693544"
  },
  {
    "id": "7494642530"
  },
  {
    "id": "7988227817"
  },
  {
    "id": "8030178242"
  },
  {
    "id": "5008576054"
  },
  {
    "id": "921355549"
  },
  {
    "id": "7437580552"
  },
  {
    "id": "7681063736"
  },
  {
    "id": "7485864656"
  },
  {
    "id": "5902476286"
  },
  {
    "id": "7501092991"
  },
  {
    "id": "8141962148"
  },
  {
    "id": "7862095887"
  },
  {
    "id": "6422497632"
  },
  {
    "id": "7951042686"
  },
  {
    "id": "7913752662"
  },
  {
    "id": "1016131375"
  },
  {
    "id": "7673911642"
  },
  {
    "id": "7315682139"
  },
  {
    "id": "7608590640"
  },
  {
    "id": "6748443374"
  },
  {
    "id": "5979848389"
  },
  {
    "id": "6925363738"
  },
  {
    "id": "5803994625"
  },
  {
    "id": "6499286760"
  },
  {
    "id": "794730612"
  },
  {
    "id": "7526264011"
  },
  {
    "id": "6832524045"
  },
  {
    "id": "7470549431"
  },
  {
    "id": "6677240177"
  },
  {
    "id": "5207891439"
  },
  {
    "id": "7411280728"
  },
  {
    "id": "7088508853"
  },
  {
    "id": "1697953345"
  },
  {
    "id": "6582740136"
  },
  {
    "id": "7046465623"
  },
  {
    "id": "6017958742"
  },
  {
    "id": "6018086671"
  },
  {
    "id": "5492664761"
  },
  {
    "id": "1345721110"
  },
  {
    "id": "914466518"
  },
  {
    "id": "6098829133"
  },
  {
    "id": "1069988712"
  },
  {
    "id": "2093585619"
  },
  {
    "id": "1600639827"
  },
  {
    "id": "2027189811"
  }
]